teams_lib_pzsp2_z1/__init__.py
teams_lib_pzsp2_z1/client.py
teams_lib_pzsp2_z1/config.py
teams_lib_pzsp2_z1/bin/teamsClientLib_linux
teams_lib_pzsp2_z1/bin/teamsClientLib_windows.exe
teams_lib_pzsp2_z1/model/__init__.py
teams_lib_pzsp2_z1/model/channel.py
teams_lib_pzsp2_z1/model/chat.py
teams_lib_pzsp2_z1/model/member.py
teams_lib_pzsp2_z1/model/mention.py
teams_lib_pzsp2_z1/model/message.py
teams_lib_pzsp2_z1/model/search.py
teams_lib_pzsp2_z1/model/team.py
teams_lib_pzsp2_z1/services/__init__.py
teams_lib_pzsp2_z1/services/base_service.py
teams_lib_pzsp2_z1/services/channels.py
teams_lib_pzsp2_z1/services/chats.py
teams_lib_pzsp2_z1/services/teams.py
teams_lib_pzsp2_z1-0.1.19.dist-info/licenses/LICENSE
teams_lib_pzsp2_z1-0.1.19.dist-info/METADATA
teams_lib_pzsp2_z1-0.1.19.dist-info/WHEEL
teams_lib_pzsp2_z1-0.1.19.dist-info/top_level.txt
teams_lib_pzsp2_z1-0.1.19.dist-info/RECORD
