Metadata-Version: 2.4
Name: teams_lib_pzsp2_z1
Version: 0.1.19
Summary: Bridge to Go client for Teams API
Requires-Python: >=3.12
License-File: LICENSE
Requires-Dist: python-dotenv>=1.0.0
Dynamic: license-file
